sanitycheck/__init__.py
sanitycheck-0.0.1.dist-info/METADATA
sanitycheck-0.0.1.dist-info/WHEEL
sanitycheck-0.0.1.dist-info/top_level.txt
sanitycheck-0.0.1.dist-info/RECORD
