Metadata-Version: 2.4
Name: sanitycheck
Version: 0.0.1
Summary: Just a simple sanity check (or is it?).
Home-page: https://example.com/sanitycheck
Author: Anonymous
Author-email: noreply@example.com
Classifier: Programming Language :: Python :: 3
Classifier: Operating System :: OS Independent
Requires-Python: >=3.6
Dynamic: author
Dynamic: author-email
Dynamic: classifier
Dynamic: description
Dynamic: description-content-type
Dynamic: home-page
Dynamic: requires-python
Dynamic: summary
